main.py
mellem-0.1.0.dist-info/METADATA
mellem-0.1.0.dist-info/WHEEL
mellem-0.1.0.dist-info/top_level.txt
mellem-0.1.0.dist-info/RECORD
