Metadata-Version: 2.4
Name: mellem
Version: 0.1.0
Summary: The mellem library
Requires-Python: >=3.12
